ipdbugger/__init__.py
ipdbugger/signals.py
ipdbugger-2.5.0.dist-info/LICENSE
ipdbugger-2.5.0.dist-info/METADATA
ipdbugger-2.5.0.dist-info/WHEEL
ipdbugger-2.5.0.dist-info/top_level.txt
ipdbugger-2.5.0.dist-info/RECORD
