Metadata-Version: 2.1
Name: ipdbugger
Version: 2.5.0
Summary: ipdb-based debugger
Home-page: https://github.com/gregoil/ipdbugger
Author: gregoil
Author-email: gregoil@walla.co.il
License: MIT
Keywords: ipdb debug debugger exception
Platform: UNKNOWN
Classifier: Programming Language :: Python :: 2
Classifier: Programming Language :: Python :: 2.7
Classifier: Programming Language :: Python :: 3
Classifier: Programming Language :: Python :: 3.5
Classifier: Programming Language :: Python :: 3.6
Requires-Python: >=2.7,!=3.0.*,!=3.1.*,!=3.2.*,!=3.3.*,!=3.4.*
Requires-Dist: ipdb
Requires-Dist: future
Requires-Dist: colorama
Requires-Dist: termcolor
Provides-Extra: dev
Requires-Dist: flake8 ; extra == 'dev'
Requires-Dist: pylint ; extra == 'dev'
Requires-Dist: pytest ; extra == 'dev'
Requires-Dist: pytest-cov ; extra == 'dev'
Requires-Dist: mock ; extra == 'dev'
